plucogen/__init__.py
plucogen/__main__.py
plucogen/api/__init__.py
plucogen/api/entrypoint.py
plucogen/api/v0/__init__.py
plucogen/api/v0/api.py
plucogen/api/v0/base.py
plucogen/api/v0/consumer.py
plucogen/api/v0/generator.py
plucogen/api/v0/handler.py
plucogen/api/v0/writer.py
plucogen/cli/__init__.py
plucogen/cli/__main__.py
plucogen/cli/api.py
plucogen/cli/parser.py
plucogen/consumers/__init__.py
plucogen/consumers/file.py
plucogen/file.py
plucogen/generators/__init__.py
plucogen/generators/cli.py
plucogen/generators/example.py
plucogen/generators/jinja/__init__.py
plucogen/generators/jinja/extensions.py
plucogen/generators/jinja/render.py
plucogen/handlers/__init__.py
plucogen/handlers/yaml/__init__.py
plucogen/handlers/yaml/api.py
plucogen/handlers/yaml/tags.py
plucogen/handlers/yaml/yaml.py
plucogen/logging.py
plucogen/util/__init__.py
plucogen/util/paths.py
plucogen/validators/__init__.py
plucogen/validators/json_schema.py
plucogen-0.2.4.dist-info/METADATA
plucogen-0.2.4.dist-info/WHEEL
plucogen-0.2.4.dist-info/entry_points.txt
plucogen-0.2.4.dist-info/RECORD
