Metadata-Version: 2.1
Name: plucogen
Version: 0.2.4
Summary: Pluggable universal code generator using dataformats like JSON and YAML to generate files with template languages like Jinja2.
License: LGPL-3
Author: Jörn Krenzer
Author-email: plucogen@joern.krenzer.space
Requires-Python: >=3.9
Classifier: License :: Other/Proprietary License
Classifier: Programming Language :: Python :: 3
Classifier: Programming Language :: Python :: 3.9
Classifier: Programming Language :: Python :: 3.10
Classifier: Programming Language :: Python :: 3.11
Requires-Dist: ConfigArgParse (>=1.5.3,<2.0.0)
Requires-Dist: Jinja2 (>=3.1.2,<4.0.0)
Requires-Dist: jsonschema[format] (>=4.17.3,<5.0.0)
Requires-Dist: ruamel.yaml[jinja2] (>=0.17.32,<0.18.0)
